LICENSE
README.md
setup.py
Deasciifier/Asciifier.c
Deasciifier/Asciifier.pxd
Deasciifier/Asciifier.pyx
Deasciifier/Deasciifier.c
Deasciifier/Deasciifier.pxd
Deasciifier/Deasciifier.pyx
Deasciifier/NGramDeasciifier.c
Deasciifier/NGramDeasciifier.pyx
Deasciifier/SimpleAsciifier.c
Deasciifier/SimpleAsciifier.pyx
Deasciifier/SimpleDeasciifier.c
Deasciifier/SimpleDeasciifier.pxd
Deasciifier/SimpleDeasciifier.pyx
Deasciifier/__init__.py
NlpToolkit_Deasciifier_Cy.egg-info/PKG-INFO
NlpToolkit_Deasciifier_Cy.egg-info/SOURCES.txt
NlpToolkit_Deasciifier_Cy.egg-info/dependency_links.txt
NlpToolkit_Deasciifier_Cy.egg-info/requires.txt
NlpToolkit_Deasciifier_Cy.egg-info/top_level.txt
nlptoolkit_deasciifier_cy.egg-info/PKG-INFO
nlptoolkit_deasciifier_cy.egg-info/SOURCES.txt
nlptoolkit_deasciifier_cy.egg-info/dependency_links.txt
nlptoolkit_deasciifier_cy.egg-info/requires.txt
nlptoolkit_deasciifier_cy.egg-info/top_level.txt