Metadata-Version: 2.4
Name: nlptoolkit-deasciifier-cy
Version: 1.0.13
Summary: Turkish Asciifier/Deasciifier Library
Home-page: https://github.com/StarlangSoftware/TurkishDeasciifier-Cy
Author: olcaytaner
Author-email: olcay.yildiz@ozyegin.edu.tr
License-File: LICENSE
Requires-Dist: NlpToolkit-MorphologicalAnalysis-Cy
Requires-Dist: NlpToolkit-NGram-Cy
Dynamic: author
Dynamic: author-email
Dynamic: description
Dynamic: description-content-type
Dynamic: home-page
Dynamic: license-file
Dynamic: requires-dist
Dynamic: summary
